molass_legacy/SysArgs.py
molass_legacy/__init__.py
molass_legacy/molass.py
molass_legacy/ATSAS/Almerge.py
molass_legacy/ATSAS/AtsasUtils.py
molass_legacy/ATSAS/AtsasVersion.py
molass_legacy/ATSAS/AutoRg.py
molass_legacy/ATSAS/AutorgRunner.py
molass_legacy/ATSAS/CorMapAnalysis.py
molass_legacy/ATSAS/Crysol.py
molass_legacy/ATSAS/DatCmp.py
molass_legacy/ATSAS/DatGnom.py
molass_legacy/ATSAS/ExecCheck.py
molass_legacy/ATSAS/__init__.py
molass_legacy/Alsaker/Bridge.py
molass_legacy/Alsaker/Compare.py
molass_legacy/Alsaker/ComparisonPlot.py
molass_legacy/Alsaker/__init__.py
molass_legacy/Alsaker/Rg code/README.pdf
molass_legacy/Alsaker/Rg code/file1-modified-for-molass.R
molass_legacy/Alsaker/Rg code/file1.R
molass_legacy/Alsaker/Rg code/file2.R
molass_legacy/Alsaker/Rg code/file3.R
molass_legacy/Alsaker/Rg code/myo2_07D_S215_0_01.dat
molass_legacy/Alsaker/Rg code/myo2_07D_S215_0_02.dat
molass_legacy/Alsaker/Rg code/myo2_07D_S215_0_03.dat
molass_legacy/Alsaker/Rg code/myo2_07D_S215_0_04.dat
molass_legacy/Alsaker/Rg code/myo2_07D_S215_0_05.dat
molass_legacy/Alsaker/Rg code/myo2_07D_S215_0_06.dat
molass_legacy/Alsaker/Rg code/myo2_07D_S215_0_07.dat
molass_legacy/Alsaker/Rg code/myo2_07D_S215_0_08.dat
molass_legacy/Alsaker/Rg code/myo2_07D_S215_0_09.dat
molass_legacy/Alsaker/Rg code/myo2_07D_S215_0_10.dat
molass_legacy/Alsaker/Rg code/oval_01C_S008_0_01.dat
molass_legacy/AutorgKek/AppVersion.py
molass_legacy/AutorgKek/AtsasTools.py
molass_legacy/AutorgKek/BiComponentSolver.py
molass_legacy/AutorgKek/ClientServer.py
molass_legacy/AutorgKek/CommandLineOptions.py
molass_legacy/AutorgKek/CommandMain.py
molass_legacy/AutorgKek/CommandMainUtils.py
molass_legacy/AutorgKek/DataModels.py
molass_legacy/AutorgKek/DataModelsAgg.py
molass_legacy/AutorgKek/DataModelsTripple.py
molass_legacy/AutorgKek/ErrorResult.py
molass_legacy/AutorgKek/Guinier.py
molass_legacy/AutorgKek/GuinierInterval.py
molass_legacy/AutorgKek/GuinierPorodFit.py
molass_legacy/AutorgKek/HeadAnomalies.py
molass_legacy-0.5.1.dist-info/METADATA
molass_legacy-0.5.1.dist-info/WHEEL
molass_legacy-0.5.1.dist-info/entry_points.txt
molass_legacy-0.5.1.dist-info/licenses/LICENSE.txt
molass_legacy-0.5.1.dist-info/RECORD
