Metadata-Version: 2.4
Name: molass_legacy
Version: 0.5.1
Summary: Matrix Optimization with Low-rank factorization for Automated analysis of SEC-SAXS
Project-URL: Repository, https://github.com/biosaxs-dev/molass-legacy
Author: Molass Community
Maintainer: Molass Community
License: GNU General Public License v3.0
License-File: LICENSE.txt
Keywords: SEC-SAXS
Classifier: Development Status :: 4 - Beta
Classifier: License :: OSI Approved :: GNU General Public License v3 (GPLv3)
Classifier: Programming Language :: Python
Requires-Python: <3.14,>=3.9
Requires-Dist: lmfit
Requires-Dist: matplotlib
Requires-Dist: molass>=0.8.0
Requires-Dist: numba
Requires-Dist: numpy
Requires-Dist: openpyxl<=3.1.3
Requires-Dist: psutil
Requires-Dist: pybaselines>=1.2.0
Requires-Dist: pyperclip
Requires-Dist: python-tkdnd
Requires-Dist: ruptures
Requires-Dist: scikit-learn
Requires-Dist: scipy
Requires-Dist: screeninfo
Requires-Dist: seaborn
Requires-Dist: statsmodels>=0.14.5
Requires-Dist: termcolor
Requires-Dist: tksheet
Requires-Dist: toml
Requires-Dist: ultranest
Requires-Dist: wmi
Provides-Extra: excel
Requires-Dist: pywin32; extra == 'excel'
